ciofcheck/__init__.py
ciofcheck/bar_chart.py
ciofcheck/cli.py
ciofcheck/icons/clip.png
ciofcheck/icons/tick.png
ciofcheck-0.1.13.dist-info/METADATA
ciofcheck-0.1.13.dist-info/WHEEL
ciofcheck-0.1.13.dist-info/entry_points.txt
ciofcheck-0.1.13.dist-info/RECORD
