Metadata-Version: 2.1
Name: ciofcheck
Version: 0.1.13
Summary: A tool for checking and analyzing image sequences
Author: Julian Mann
Author-email: jmann@coreweave.com
Requires-Python: ==3.11.9
Classifier: Programming Language :: Python :: 3
Requires-Dist: cioseq (>=0.5.1,<0.6.0)
Requires-Dist: matplotlib (>=3.10.0,<4.0.0)
Requires-Dist: mplcursors (>=0.6.0,<0.7.0)
Requires-Dist: numpy (>=2.2.0,<3.0.0)
Requires-Dist: pyperclip (>=1.9.0,<2.0.0)
